{
 "": {
    "name": "JWM Asia (Singapore) Pte LTD",
    "website": "www.jwmasia.com"
  },
  "xx": {
    "name": "深圳盛和果篮子有限公司",
    "website": ""
  },
  "x3": {
    "name": "湖南尚溪贸易有限公司",
    "website": ""
  },
  "x4": {
    "name": "湖南汤易食品有限公司",
    "website": ""
  },
  "x5": {
    "name": "深圳市清湸保洁服务有限责任公司",
    "website": ""
  },
  "x6": {
    "name": "深圳市英然贸易有限责任公司",
    "website": ""
  },
  "x7": {
    "name": "亿丰贸易（私人）有限公司（马来西亚）",
    "website": ""
  },
  "x8": {
    "name": "亿丰贸易（私人）有限公司（马来西亚）",
    "website": ""
  },
}